{
    "packages": [],
    "includes": {
        "include/all$03dc056e8212b0e9beb776ae37cadd142e7ec7f7.json": {
            "sha1": "03dc056e8212b0e9beb776ae37cadd142e7ec7f7"
        }
    },
    "metadata-url": "/satis/p2/%package%.json",
    "available-packages": [
        "inflexyon/payment",
        "jerome-rdlv/advanced-custom-fields-pro",
        "jerome-rdlv/allow-svg",
        "jerome-rdlv/boond-manager",
        "jerome-rdlv/cachebust-assets",
        "jerome-rdlv/cf7-tac-recaptcha",
        "jerome-rdlv/cpt-parent",
        "jerome-rdlv/custom-scripts",
        "jerome-rdlv/email-smtp",
        "jerome-rdlv/html-manipulation",
        "jerome-rdlv/mailjet-api",
        "jerome-rdlv/outgoing-ip",
        "jerome-rdlv/post-order",
        "jerome-rdlv/registry",
        "jerome-rdlv/sywo",
        "jerome-rdlv/translation-update",
        "jerome-rdlv/webp-images",
        "jerome-rdlv/wp-translation-update"
    ]
}
