{
    "packages": [],
    "includes": {
        "include/all$65bcbd24f27d0b4b01652b241125642d2ca7807c.json": {
            "sha1": "65bcbd24f27d0b4b01652b241125642d2ca7807c"
        }
    },
    "metadata-url": "/satis/p2/%package%.json",
    "available-packages": [
        "bea/acf-options-for-polylang",
        "inflexyon/payment",
        "jerome-rdlv/allow-svg",
        "jerome-rdlv/boond-manager",
        "jerome-rdlv/cachebust-assets",
        "jerome-rdlv/cf7-tac-recaptcha",
        "jerome-rdlv/cpt-parent",
        "jerome-rdlv/custom-scripts",
        "jerome-rdlv/email-smtp",
        "jerome-rdlv/html-manipulation",
        "jerome-rdlv/mailjet-api",
        "jerome-rdlv/outgoing-ip",
        "jerome-rdlv/post-order",
        "jerome-rdlv/registry",
        "jerome-rdlv/sywo",
        "jerome-rdlv/translation-update",
        "jerome-rdlv/webp-images",
        "jerome-rdlv/wp-translation-update"
    ]
}
